{"version":1,"resource":"file:///home/sb/StoxAlpha/alpha-hft/broker/smartapi/smartapi_ws_login.go","entries":[{"id":"SY0j.go","timestamp":1692761124838},{"id":"CRhe.go","timestamp":1692761154021},{"id":"FHhi.go","timestamp":1692761191729},{"id":"88Rw.go","source":"Organize Imports","timestamp":1692761249229},{"id":"Bugs.go","source":"Organize Imports","timestamp":1692761285490},{"id":"SQfA.go","timestamp":1692761350031},{"id":"OE2g.go","timestamp":1692761491338},{"id":"rax3.go","timestamp":1692761518151},{"id":"RNB4.go","timestamp":1692761541663},{"id":"5FaY.go","timestamp":1692761775686},{"id":"GZU3.go","timestamp":1692761818678},{"id":"9edb.go","timestamp":1692761938660},{"id":"JvDM.go","timestamp":1692761962880},{"id":"44DS.go","timestamp":1692761990660},{"id":"7Ra0.go","timestamp":1692762009554},{"id":"RAEe.go","timestamp":1692762026721},{"id":"6odk.go","source":"Organize Imports","timestamp":1692762128523},{"id":"2Qhh.go","timestamp":1692762148797},{"id":"F5PN.go","source":"Organize Imports","timestamp":1692762152260},{"id":"bg7o.go","timestamp":1692762187147},{"id":"rE02.go","timestamp":1692762201727},{"id":"CZmB.go","source":"Organize Imports","timestamp":1692762205357},{"id":"vmk9.go","timestamp":1692762210067}]}